photoshow/__init__.py
photoshow/__main__.py
photoshow/_photoshow.py
photoshow-1.0.8.dist-info/LICENCE.txt
photoshow-1.0.8.dist-info/METADATA
photoshow-1.0.8.dist-info/WHEEL
photoshow-1.0.8.dist-info/top_level.txt
photoshow-1.0.8.dist-info/RECORD
