Metadata-Version: 2.1
Name: photoshow
Version: 1.0.8
Summary: Full screen photo slideshow
Home-page: https://github.com/rikfair/photoshow
Author: rikfair
Author-email: mail4rik-pypi@yahoo.com
License: MIT
Project-URL: Bug Tracker, https://github.com/rikfair/photoshow/issues
Project-URL: Documentation, https://photoshow.readthedocs.io/
Classifier: Development Status :: 5 - Production/Stable
Classifier: Intended Audience :: Developers
Classifier: License :: OSI Approved :: MIT License
Classifier: Operating System :: OS Independent
Classifier: Programming Language :: Python :: 3
Classifier: Programming Language :: Python :: 3 :: Only
Classifier: Topic :: Multimedia :: Graphics :: Presentation
Classifier: Topic :: Multimedia :: Graphics :: Viewers
Requires-Python: >=3.7
License-File: LICENCE.txt
Requires-Dist: piexif (>=1.1.3)
Requires-Dist: Pillow (>=9.1.0)
